ascii_canvas/__init__.py
ascii_canvas/canvas.py
ascii_canvas/item.py
ascii_canvas-2.0.0.dist-info/LICENSE
ascii_canvas-2.0.0.dist-info/METADATA
ascii_canvas-2.0.0.dist-info/WHEEL
ascii_canvas-2.0.0.dist-info/RECORD
