Metadata-Version: 2.1
Name: ascii-canvas
Version: 2.0.0
Summary: Treat strings like Items on a 2D Canvas.
Author: Paul Schweizer
Author-email: paulschweizer@gmx.net
Requires-Python: >=3.10,<4.0
Classifier: Programming Language :: Python :: 3
Classifier: Programming Language :: Python :: 3.10
Classifier: Programming Language :: Python :: 3.11
